README.rst
setup.py
genscrapeclient/__init__.py
genscrapeclient/rest.py
genscrapeclient.egg-info/PKG-INFO
genscrapeclient.egg-info/SOURCES.txt
genscrapeclient.egg-info/dependency_links.txt
genscrapeclient.egg-info/requires.txt
genscrapeclient.egg-info/top_level.txt