Metadata-Version: 1.0
Name: genscrapeclient
Version: 0.2.1
Summary: Client API library for the Genscrape API
Home-page: http://kodeplay.com
Author: Vineet Naik
Author-email: vineet.naik@kodeplay.com
License: MIT License
Platform: UNKNOWN
